twd/__init__.py
twd/cli.py
twd/config.py
twd/data.py
twd/tui.py
twd/tui.tcss
twd/utils.py
twd/modals/__init__.py
twd/modals/confirm.py
twd/modals/edit.py
twd_m4sc0-3.1.1.dist-info/METADATA
twd_m4sc0-3.1.1.dist-info/WHEEL
twd_m4sc0-3.1.1.dist-info/entry_points.txt
twd_m4sc0-3.1.1.dist-info/top_level.txt
twd_m4sc0-3.1.1.dist-info/RECORD
