Metadata-Version: 2.4
Name: twd-m4sc0
Version: 3.1.1
Summary: TWD by m4sc0
Author: m4sc0
License: MIT
Project-URL: Homepage, https://github.com/m4sc0/twd
Classifier: Programming Language :: Python :: 3
Classifier: License :: OSI Approved :: MIT License
Classifier: Operating System :: OS Independent
Requires-Python: >=3.13
Requires-Dist: click>=8
Requires-Dist: textual>=7.2
Requires-Dist: pydantic>=2.12
Requires-Dist: RapidFuzz>=3.14
